QttNot/__main__.py
QttNot-0.1.0.dist-info/METADATA
QttNot-0.1.0.dist-info/RECORD
QttNot-0.1.0.dist-info/WHEEL
QttNot-0.1.0.dist-info/entry_points.txt
QttNot-0.1.0.dist-info/pbr.json
QttNot-0.1.0.dist-info/top_level.txt
