Metadata-Version: 2.1
Name: QttNot
Version: 0.1.0
Summary: Notification from Mqtt
Home-page: https://framagit.org/who0/QttNot
Author: Just Me
Author-email: notme@gmail.com
License: GNU General Public License v3.0
Platform: UNKNOWN
Classifier: Programming Language :: Python :: 3
Classifier: Intended Audience :: Information Technology
Classifier: Intended Audience :: End Users/Desktop
Classifier: Development Status :: 4 - Beta
Classifier: Environment :: Console
Classifier: License :: OSI Approved :: GNU General Public License v3 (GPLv3)
